firedust/__init__.py
firedust/_assistant/abilities/__init__.py
firedust/_assistant/abilities/base.py
firedust/_assistant/base/__init__.py
firedust/_assistant/base/assistant.py
firedust/_assistant/chat/__init__.py
firedust/_assistant/chat/base.py
firedust/_assistant/interface/__init__.py
firedust/_assistant/interface/base.py
firedust/_assistant/interface/slack.py
firedust/_assistant/learning/__init__.py
firedust/_assistant/learning/base.py
firedust/_assistant/memory/__init__.py
firedust/_assistant/memory/base.py
firedust/_data/embed.py
firedust/_data/safetycheck.py
firedust/entrypoint/__init__.py
firedust/entrypoint/assistant.py
firedust/entrypoint/data/__init__.py
firedust/py.typed
firedust/types/__init__.py
firedust/types/api.py
firedust/types/assistant.py
firedust/types/base.py
firedust/types/chat.py
firedust/types/interface.py
firedust/types/memory.py
firedust/types/safety.py
firedust/types/tools.py
firedust/utils/__init__.py
firedust/utils/api.py
firedust/utils/checks.py
firedust/utils/errors.py
firedust/utils/inference_input_support.py
firedust/utils/logging.py
firedust-0.0.73.dist-info/LICENSE
firedust-0.0.73.dist-info/METADATA
firedust-0.0.73.dist-info/WHEEL
firedust-0.0.73.dist-info/RECORD
