Metadata-Version: 2.1
Name: firedust
Version: 0.0.73
Summary: A simple framework to build and deploy AI tools.
Author: ion
Author-email: firedvst@gmail.com
Requires-Python: >=3.8,<3.13
Classifier: Programming Language :: Python :: 3
Classifier: Programming Language :: Python :: 3.8
Classifier: Programming Language :: Python :: 3.9
Classifier: Programming Language :: Python :: 3.10
Classifier: Programming Language :: Python :: 3.11
Classifier: Programming Language :: Python :: 3.12
Requires-Dist: httpx (>=0.26.0,<0.27.0)
Requires-Dist: pydantic (>=2.5.3,<3.0.0)
